lxgolaxy/__init__.py
lxgolaxy/config.py
lxgolaxy/encrypt.py
lxgolaxy-1.0.1.dist-info/LICENSE.txt
lxgolaxy-1.0.1.dist-info/METADATA
lxgolaxy-1.0.1.dist-info/WHEEL
lxgolaxy-1.0.1.dist-info/top_level.txt
lxgolaxy-1.0.1.dist-info/RECORD
