Metadata-Version: 2.1
Name: lxgolaxy
Version: 1.0.1
Summary: Private configuration information !
Home-page: https://pypi.org/project/lxgolaxy
Author: lx
Author-email: 125066648@qq.com
License: UNKNOWN
Platform: all
Requires-Dist: wheel
